LICENSE.txt
MANIFEST.in
README.rst
setup.cfg
setup.py
versioneer.py
src/PyGIRAFE.egg-info/PKG-INFO
src/PyGIRAFE.egg-info/SOURCES.txt
src/PyGIRAFE.egg-info/dependency_links.txt
src/PyGIRAFE.egg-info/entry_points.txt
src/PyGIRAFE.egg-info/top_level.txt
src/girafe/__init__.py
src/girafe/__main__.py
src/girafe/_version.py
src/girafe/analysis/__init__.py
src/girafe/analysis/cicada_analysis_nwb_wrapper.py
src/girafe/analysis/girafe_analysis.py
src/girafe/analysis/girafe_analysis_arguments_handler.py
src/girafe/analysis/girafe_analysis_format_wrapper.py
src/girafe/analysis/ci_analyses/__init__.py
src/girafe/analysis/ci_analyses/cicada_activity_intervals_ratio_analysis.py
src/girafe/analysis/ci_analyses/cicada_activity_sum_auto_correlation_analysis.py
src/girafe/analysis/ci_analyses/cicada_analysis_pairwise_similarity.py
src/girafe/analysis/ci_analyses/cicada_assemblies_core_analysis.py
src/girafe/analysis/ci_analyses/cicada_assemblies_gonzalez_analysis.py
src/girafe/analysis/ci_analyses/cicada_assemblies_ica_cs_analysis.py
src/girafe/analysis/ci_analyses/cicada_assemblies_ica_mp_analysis.py
src/girafe/analysis/ci_analyses/cicada_assemblies_malvache_analysis.py
src/girafe/analysis/ci_analyses/cicada_assemblies_promax_cs_analysis.py
src/girafe/analysis/ci_analyses/cicada_assemblies_promax_mp_analysis.py
src/girafe/analysis/ci_analyses/cicada_assemblies_russo_analysis.py
src/girafe/analysis/ci_analyses/cicada_assemblies_sgc_analysis.py
src/girafe/analysis/ci_analyses/cicada_assemblies_svd_analysis.py
src/girafe/analysis/ci_analyses/cicada_assemblies_tavoni_analysis.py
src/girafe/analysis/ci_analyses/cicada_behavior_quantification_analysis.py
src/girafe/analysis/ci_analyses/cicada_cell_ass_vs_intervals_analysis.py
src/girafe/analysis/ci_analyses/cicada_cells_map_analysis.py
src/girafe/analysis/ci_analyses/cicada_cells_maps_fusion_analysis.py
src/girafe/analysis/ci_analyses/cicada_citnps_analysis.py
src/girafe/analysis/ci_analyses/cicada_connectivity_graph.py
src/girafe/analysis/ci_analyses/cicada_connectivity_graphs_description.py
src/girafe/analysis/ci_analyses/cicada_deep_cinac_prediction_analysis.py
