Metadata-Version: 2.1
Name: PyGIRAFE
Version: 1.0.0
Summary: A Python Analyses Toolbox
Home-page: https://github.com/pappyhammer/pygirafe
Author: Julien Denis
Author-email: julien.denis3@gmail.com
License: UNKNOWN
Project-URL: Bug Reports, https://github.com/pappyhammer/PyGIRAFE/issues
Project-URL: Source, https://github.com/pappyhammer/PyGIRAFE/tree/master/src
Keywords: girafe pygirafez
Platform: UNKNOWN
Classifier: Development Status :: 4 - Beta
Classifier: Intended Audience :: Science/Research
Classifier: License :: OSI Approved :: MIT License
Classifier: Programming Language :: Python :: 3.6
Classifier: Programming Language :: Python :: 3.7
Requires-Python: >=3.5, <4
